{
  "blocked_reasons": [],
  "can_update_demo_status": false,
  "can_update_mvp_status": false,
  "can_update_post_mvp_gate_status": true,
  "claim_boundary": "continuous_kv_joint_readiness_gate_no_demo_or_wallclock_speedup_claim",
  "claim_limitations": [
    "Joint verifier only; it does not itself execute live traffic.",
    "KV prefix reuse must be server-observed tensor/cache reuse; metadata-only reports fail closed.",
    "Wall-clock speedup and demo-safety promotion remain separate gates."
  ],
  "continuous_batching": {
    "batched_tick_count": 1,
    "claim_boundary": "verified_live_continuous_batching_server_concurrent_arrival_parity",
    "late_arrival_observed": true,
    "live_server_late_arrival_parity_proven": true,
    "logits_fingerprint_parity_proven": true,
    "logits_numeric_parity_proven": false,
    "logits_parity_proven": true,
    "status": "passed"
  },
  "continuous_batching_ready": true,
  "joint_batch_kv_ready": true,
  "kv_prefix_reuse": {
    "claim_boundary": "verified_kv_prefix_reuse_same_prefix_varied_suffix_parity_timing",
    "live_kv_cache_reuse_proven": true,
    "same_prefix_varied_suffix_proven": true,
    "server_observed_kv_cache_reuse": true,
    "speedup_proven": true,
    "status": "passed",
    "timing_measured": true
  },
  "kv_prefix_reuse_ready": true,
  "model_id": "TinyLlama/TinyLlama-1.1B-Chat-v1.0",
  "proof_status_update": {
    "continuous_batching": "passed",
    "continuous_kv_joint_readiness": "passed",
    "kv_prefix_reuse": "passed"
  },
  "source": "continuous_kv_joint_readiness.py",
  "speedup_proven": false,
  "verification_status": "passed",
  "wallclock_speedup_proven": false
}
